dressing/__init__.py
dressing/__main__.py
dressing/_compat.py
dressing/cli.py
dressing/core.py
dressing/errors.py
dressing/posix.py
dressing/utils.py
dressing/version.py
dressing/win.py
dressing-0.0.3.dist-info/LICENSE.txt
dressing-0.0.3.dist-info/METADATA
dressing-0.0.3.dist-info/WHEEL
dressing-0.0.3.dist-info/entry_points.txt
dressing-0.0.3.dist-info/top_level.txt
dressing-0.0.3.dist-info/RECORD
